mitm/__init__.py
mitm/core.py
mitm/crypto.py
mitm/mitm.py
mitm/extension/__init__.py
mitm/extension/middleware.py
mitm/extension/protocol.py
mitm-1.5.0.dist-info/AUTHORS
mitm-1.5.0.dist-info/LICENSE
mitm-1.5.0.dist-info/METADATA
mitm-1.5.0.dist-info/WHEEL
mitm-1.5.0.dist-info/pbr.json
mitm-1.5.0.dist-info/top_level.txt
mitm-1.5.0.dist-info/RECORD
