Metadata-Version: 2.1
Name: mitm
Version: 1.5.0
Summary: Man-in-the-middle proxy with customizable options.
Home-page: https://github.com/synchronizing/mitm
Author: Felipe Faria
Author-email: felipefaria@me.com
License: MIT
Project-URL: Bug Tracker, https://github.com/synchronizing/mitm/issues
Project-URL: Documentation, https://synchronizing.github.io/mitm/
Project-URL: Source Code, https://github.com/synchronizing/mitm/tree/master
Keywords: mitm
Classifier: Programming Language :: Python :: Implementation :: CPython
Classifier: Development Status :: 5 - Production/Stable
Classifier: License :: OSI Approved :: MIT License
Classifier: Natural Language :: English
Classifier: Topic :: Software Development :: Libraries
Classifier: Topic :: Utilities
Requires-Python: >=3.5
License-File: LICENSE
License-File: AUTHORS
Requires-Dist: pbr (==5.9.0)
Requires-Dist: PyOpenSSL (==23.1.1)
Requires-Dist: appdirs (==1.4.4)
Requires-Dist: httpq (==1.2.0)
Requires-Dist: toolbox (==1.11.0)
Provides-Extra: dev
Requires-Dist: pytest ; extra == 'dev'
Requires-Dist: pytest-cov ; extra == 'dev'
Requires-Dist: pytest-asyncio ; extra == 'dev'
Requires-Dist: coveralls ; extra == 'dev'
Requires-Dist: sphinx ; extra == 'dev'
Requires-Dist: sphinx-copybutton ; extra == 'dev'
Requires-Dist: sphinx-autobuild ; extra == 'dev'
Requires-Dist: furo ; extra == 'dev'
